judie/__init__.py
judie/generator.py
judie/store.py
judie/types.py
judie/evaluators/__init__.py
judie/evaluators/base.py
judie/evaluators/gacha.py
judie/evaluators/simple.py
judie-0.0.2.dist-info/licenses/LICENSE
judie-0.0.2.dist-info/METADATA
judie-0.0.2.dist-info/WHEEL
judie-0.0.2.dist-info/top_level.txt
judie-0.0.2.dist-info/RECORD
