Metadata-Version: 2.4
Name: judie
Version: 0.0.2
Summary: Judge and evaluate your chunk quality with Judie, the Owl! Quick, easy, and effective!
Author: Bhavnick Minhas, Shreyash Nigam
Maintainer: Bhavnick Minhas, Shreyash Nigam
License-Expression: Apache-2.0
Project-URL: Homepage, https://github.com/chonkie-inc/judie
Project-URL: Repository, https://github.com/chonkie-inc/judie
Project-URL: Documentation, https://github.com/chonkie-inc/judie#readme
Project-URL: Bug Tracker, https://github.com/chonkie-inc/judie/issues
Keywords: chunking,rag,llm,evaluation,nlp,information-retrieval
Classifier: Development Status :: 3 - Alpha
Classifier: Intended Audience :: Developers
Classifier: Intended Audience :: Science/Research
Classifier: Operating System :: OS Independent
Classifier: Programming Language :: Python :: 3
Classifier: Programming Language :: Python :: 3.10
Classifier: Programming Language :: Python :: 3.11
Classifier: Programming Language :: Python :: 3.12
Classifier: Programming Language :: Python :: 3.13
Classifier: Topic :: Scientific/Engineering :: Artificial Intelligence
Classifier: Topic :: Software Development :: Libraries :: Python Modules
Classifier: Topic :: Text Processing :: Linguistic
Requires-Python: >=3.10
License-File: LICENSE
Requires-Dist: chonkie[all]<1.1.0,>=1.0.0
Requires-Dist: datasets>=2.0.0
Provides-Extra: dev
Requires-Dist: ruff; extra == "dev"
Requires-Dist: pytest>=6.0; extra == "dev"
Requires-Dist: pytest-cov; extra == "dev"
Requires-Dist: mypy; extra == "dev"
Dynamic: license-file
